[{"time": "2026-04-27 05:27", "result": "\u7121\u7968\uff08\u5168\u90e8 Sold out\uff09"}, {"time": "2026-04-27 05:50", "result": "\u7121\u7968\uff08\u5168\u90e8 Sold out\uff09"}, {"time": "2026-04-27 08:14", "result": "\u7121\u7968\uff08\u5168\u90e8 Sold out\uff09"}, {"time": "2026-04-27 11:00", "result": "\u7121\u7968\uff08\u5168\u90e8 Sold out\uff09"}, {"time": "2026-04-27 12:22", "result": "\u7121\u7968\uff08\u5168\u90e8 Sold out\uff09"}, {"time": "2026-04-27 15:04", "result": "\u7121\u7968\uff08\u5168\u90e8 Sold out\uff09"}]